{"whitelist": null, "plugins": null, "signs": [], "id": 145992, "plugins_fml": ["mcp", "FML", "Forge", "appliedenergistics2-core", "CodeChickenCore", "MobiusCore", "NotEnoughItems", "OpenEye", "OpenModsCore", "<CoFH ASM>", "furnace3d", "bspkrsCore", "StartingInventory", "appliedenergistics2", "bdlib", "ae2stuff", "ImmibisCore", "AutoFood", "CoFHCore", "MineFactoryReloaded", "Baubles", "Thaumcraft", "MineFactoryReloaded|CompatThaumcraft", "Waila", "Automagy", "autopackager", "BiblioCraft", "Mantle", "Natura", "BiblioWoodsNatura", "ThermalFoundation", "ThermalExpansion", "BigReactors", "Botania", "CarpentersBlocks", "ChickenChunks", "ForgeMultipart", "chisel", "ComputerCraft", "CosmeticArmor", "props", "DraconicEvolution", "DragonMounts", "Emotes", "EnderIO", "EnderStorage", "EnderTech", "enderutilities", "exnihilo", "RedstoneArsenal", "TConstruct", "exastris", "extracells", "ExtraTiC", "ExtraUtilities", "FoodPlus", "ForbiddenMagic", "foxlib", "GregsLighting", "iChunUtil", "Hats", "HatStand", "headcrumbs", "inventorytweaks", "IronChest", "ItsRainingFood", "JABBA", "LiquidXP", "lootbags", "LunatriusCore", "magicalcrops", "mfrmagiccropscompat", "MineFactoryReloaded|CompatAppliedEnergistics", "MineFactoryReloaded|CompatAtum", "MineFactoryReloaded|CompatBackTools", "MineFactoryReloaded|CompatBuildCraft", "MineFactoryReloaded|CompatChococraft", "MineFactoryReloaded|CompatExtraBiomes", "MineFactoryReloaded|CompatForestry", "MineFactoryReloaded|CompatForgeMicroblock", "MineFactoryReloaded|CompatIC2", "MineFactoryReloaded|CompatMystcraft", "MineFactoryReloaded|CompatProjRed", "MineFactoryReloaded|CompatRailcraft", "MineFactoryReloaded|CompatSufficientBiomes", "MineFactoryReloaded|CompatThermalExpansion", "MineFactoryReloaded|CompatTConstruct", "MineFactoryReloaded|CompatTwilightForest", "MineFactoryReloaded|CompatVanilla", "MineTweaker3", "modtweaker2", "Morpheus", "NEIAddons", "NEIAddons|Botany", "NEIAddons|Forestry", "NEIAddons|CraftingTables", "NEIAddons|ExNihilo", "neiintegration", "OpenMods", "OpenBlocks", "OpenPeripheralCore", "OpenPeripheral", "OpenPeripheralIntegration", "MapWriter", "Opis", "RedLogic", "libsandstone", "xreliquary", "rftools", "ttCore", "SimpleAchievements", "simplyjetpacks", "slabcraftmod", "SolarFlux", "staircraftmod", "Sync", "TabulaRasa", "tcnodetracker", "thaumcraftneiplugin", "thaumicenergistics", "ThermalCasting", "ThermalDynamics", "Translocator", "treeGrowingSimulator", "UtilityMobs", "WailaHarvestability", "WailaNBT", "wawla", "witchery", "WR-CBE|Core", "WR-CBE|Addons", "WR-CBE|Logic", "YUNoMakeGoodMap", "McMultipart", "IguanaTweaksTConstruct", "MooFluids", "RanchableFluidCows", "ForgeMicroblock"], "gamemode": null, "port": 25565, "state": "whitelist", "version": "1.7.10", "online": true, "protocol_version": 5, "max_player_count": 20, "level_type": null, "description": "A Minecraft Server", "brand": null, "welcome": null, "difficulty": null, "host": "104.238.147.58", "help_p1": null, "player_count": 0, "players": null, "error": "Invalid token", "hardcore": null, "software": null}
{"whitelist": null, "plugins": null, "signs": [], "id": 55828, "plugins_fml": null, "gamemode": null, "port": 25565, "state": "whitelist", "version": "Spigot 1.9.2", "online": true, "protocol_version": 109, "max_player_count": 8, "level_type": null, "description": "A Minecraft Server", "brand": null, "welcome": null, "difficulty": null, "host": "76.106.26.150", "help_p1": null, "player_count": 0, "players": null, "error": "Invalid token", "hardcore": null, "software": null}
{"whitelist": null, "plugins": null, "signs": [], "id": 280466, "plugins_fml": null, "gamemode": null, "port": 25565, "state": "whitelist", "version": "CraftBukkit 1.9", "online": true, "protocol_version": 107, "max_player_count": 20, "level_type": null, "description": "Hal's Sand Box.  Be Nice.  Obey the Admin", "brand": null, "welcome": null, "difficulty": null, "host": "69.175.47.245", "help_p1": null, "player_count": 0, "players": null, "error": "Invalid token", "hardcore": null, "software": null}
{"whitelist": null, "plugins": null, "signs": [], "id": 246987, "plugins_fml": null, "gamemode": null, "port": 25565, "state": "whitelist", "version": "Spigot 1.8.8", "online": true, "protocol_version": 47, "max_player_count": 175, "level_type": null, "description": "", "brand": null, "welcome": null, "difficulty": null, "host": "198.27.108.114", "help_p1": null, "player_count": 2, "players": ["NerdyTelevision", "AdrianooDK"], "error": "Invalid token", "hardcore": null, "software": null}
{"whitelist": null, "plugins": null, "signs": [], "id": 224674, "plugins_fml": null, "gamemode": null, "port": 25565, "state": "connect", "version": "Spigot 1.9.2", "online": true, "protocol_version": 109, "max_player_count": 100, "level_type": null, "description": "--=[DarCraft]=--                                           Welcome! :D", "brand": null, "welcome": null, "difficulty": null, "host": "darcraft.net", "help_p1": null, "player_count": 9, "players": ["liljohn83006", "Shadow_Neko772", "Brookeee", "KongMathias", "xX_H_Jack_Xx", "WILDNESS17", "_Yandere_Chan_", "Best_", "NotAmazingKiara"], "error": "[Errno 110] Connection timed out", "hardcore": null, "software": null}
{"whitelist": null, "plugins": null, "signs": [], "id": 37019, "plugins_fml": null, "gamemode": null, "port": 25565, "state": "whitelist", "version": "1.9.2", "online": true, "protocol_version": 109, "max_player_count": 10, "level_type": null, "description": "A CreeperHost Server!", "brand": null, "welcome": null, "difficulty": null, "host": "192.3.26.202", "help_p1": null, "player_count": 0, "players": null, "error": "Invalid token", "hardcore": null, "software": null}
{"whitelist": null, "plugins": null, "signs": [], "id": 225651, "plugins_fml": null, "gamemode": null, "port": 25565, "state": "whitelist", "version": "1.9.2", "online": true, "protocol_version": 109, "max_player_count": 20, "level_type": null, "description": "A Minecraft Server", "brand": null, "welcome": null, "difficulty": null, "host": "80.229.25.251", "help_p1": null, "player_count": 0, "players": null, "error": "Invalid token", "hardcore": null, "software": null}
{"whitelist": null, "plugins": null, "signs": [], "id": 141519, "plugins_fml": null, "gamemode": null, "port": 25565, "state": "whitelist", "version": "1.9", "online": true, "protocol_version": 107, "max_player_count": 20, "level_type": null, "description": "A Minecraft Server", "brand": null, "welcome": null, "difficulty": null, "host": "31.209.16.118", "help_p1": null, "player_count": 0, "players": null, "error": "Invalid token", "hardcore": null, "software": null}
{"whitelist": false, "plugins": null, "signs": [{"y": 67, "x": -351, "z": 20081, "lines": ["\u0413\u041e\u041d\u042f ", "", "", ""]}, {"y": 67, "x": -350, "z": 20081, "lines": ["dsfsdf", "", "", ""]}, {"y": 67, "x": -350, "z": 20080, "lines": ["dsfdsffds", "", "", ""]}], "id": 4514, "plugins_fml": null, "gamemode": 0, "port": 25565, "state": "help", "version": "1.8.9", "online": true, "protocol_version": 47, "max_player_count": 20, "level_type": "default", "description": "HangerWorld", "brand": "vanilla", "welcome": null, "difficulty": 1, "host": "146.185.128.75", "help_p1": null, "player_count": 0, "players": null, "error": null, "hardcore": false, "software": null}
{"whitelist": null, "plugins": null, "signs": [], "id": 37074, "plugins_fml": ["mcp", "FML", "Forge", "lucky"], "gamemode": null, "port": 25565, "state": "whitelist", "version": "1.7.10", "online": true, "protocol_version": 5, "max_player_count": 5, "level_type": null, "description": "A Minecraft Server", "brand": null, "welcome": null, "difficulty": null, "host": "64.156.14.109", "help_p1": null, "player_count": 0, "players": null, "error": "Invalid token", "hardcore": null, "software": null}
{"whitelist": null, "plugins": null, "signs": [], "id": 101238, "plugins_fml": ["mcp", "FML", "Forge", "kimagine", "appliedenergistics2-core", "CodeChickenCore", "Micdoodlecore", "NotEnoughItems", "PlayerAPI", "ThaumicTinkerer-preloader", "VeinMiner_coremod", "OpenModsCore", "<CoFH ASM>", "lucky", "divinerpg", "appliedenergistics2", "MovingWorld", "ArchimedesShipsPlus", "Baubles", "Artifacts", "BiblioCraft", "CoFHCore", "ThermalFoundation", "ThermalExpansion", "BigReactors", "BiomesOPlenty", "AWWayofTime", "qmunitylib", "bluepower", "botanicgarden", "BuildCraft|Core", "BuildCraft|Builders", "BuildCraft|Transport", "BuildCraft|Energy", "BuildCraft|Silicon", "BuildCraft|Robotics", "BuildCraft|Factory", "BuildCraft|Compat", "CarpentersBlocks", "ChickenChunks", "Thaumcraft", "TwilightForest", "chisel", "chocolateQuest", "BuildMod", "CoroPets", "CoroAI", "ExtendedRenderer", "ConfigMod", "menagerie", "DeadlyWorld", "PTRModelLib", "props", "doggystyle", "DraconicEvolution", "MineFactoryReloaded", "EnderIO", "EnderStorage", "ExtraUtilities", "Waila", "ThaumicTinkerer", "ForbiddenMagic", "fossil", "GalacticraftCore", "GalacticraftMars", "Growthcraft", "Growthcraft|Cellar", "Growthcraft|Apples", "Growthcraft|Grapes", "Growthcraft|Hops", "guideapi", "iChunUtil", "Hats", "InfernalMobs", "InventoryPets", "inventorytweaks", "IrishLuck", "IronChest", "ItFellFromTheSky", "JABBA", "magicalcrops", "malisiscore", "malisisdoors", "Mantle", "RadixCore", "MCA", "MineFactoryReloaded|CompatAppliedEnergistics", "MineFactoryReloaded|CompatAtum", "MineFactoryReloaded|CompatBackTools", "MineFactoryReloaded|CompatBuildCraft", "MineFactoryReloaded|CompatChococraft", "MineFactoryReloaded|CompatExtraBiomes", "MineFactoryReloaded|CompatForestry", "MineFactoryReloaded|CompatForgeMicroblock", "MineFactoryReloaded|CompatIC2", "MineFactoryReloaded|CompatMystcraft", "MineFactoryReloaded|CompatProjRed", "MineFactoryReloaded|CompatRailcraft", "MineFactoryReloaded|CompatSufficientBiomes", "MineFactoryReloaded|CompatThaumcraft", "MineFactoryReloaded|CompatThermalExpansion", "TConstruct", "MineFactoryReloaded|CompatTConstruct", "MineFactoryReloaded|CompatTwilightForest", "MineFactoryReloaded|CompatVanilla", "MineTweaker3", "Morph", "NetherOres", "OpenMods", "OpenBlocks", "harvestcraft", "RandomThings", "RedstoneArsenal", "libsandstone", "xreliquary", "secretroomsmod", "thaumicenergistics", "ThermalDynamics", "TMechworks", "tropicraft", "VeinMiner", "VeinMinerModSupport", "witchery", "IguanaTweaksTConstruct"], "gamemode": null, "port": 25565, "state": "whitelist", "version": "thermos,cauldron,craftbukkit,mcpc,kcauldron,fml,forge 1.7.10", "online": true, "protocol_version": 5, "max_player_count": 20, "level_type": null, "description": "Jacks Crundeecraft", "brand": null, "welcome": null, "difficulty": null, "host": "109.169.56.43", "help_p1": null, "player_count": 0, "players": null, "error": "Invalid token", "hardcore": null, "software": null}
{"whitelist": null, "plugins": null, "signs": [], "id": 97522, "plugins_fml": null, "gamemode": null, "port": 25565, "state": "whitelist", "version": "1.7.4", "online": true, "protocol_version": 4, "max_player_count": 10, "level_type": null, "description": "Kopfkino Minecraft Server", "brand": null, "welcome": null, "difficulty": null, "host": "178.254.33.90", "help_p1": null, "player_count": 0, "players": null, "error": "Connection was closed from this end", "hardcore": null, "software": null}
{"whitelist": null, "plugins": null, "signs": [], "id": 77660, "plugins_fml": null, "gamemode": null, "port": 25565, "state": "whitelist", "version": "1.9", "online": true, "protocol_version": 107, "max_player_count": 4, "level_type": null, "description": "A Minecraft Server", "brand": null, "welcome": null, "difficulty": null, "host": "70.186.195.156", "help_p1": null, "player_count": 0, "players": null, "error": "Connection was closed from this end", "hardcore": null, "software": null}
{"whitelist": null, "plugins": null, "signs": [], "id": 35940, "plugins_fml": ["mcp", "FML", "Forge", "appliedenergistics2-core", "CodeChickenCore", "NotEnoughItems", "ThE-core", "ThaumicTinkerer-preloader", "ChocoPatcher", "OpenModsCore", "<CoFH ASM>", "BinniePatcher", "FastCraft", "IC2", "AdvancedSolarPanel", "AgriCraft", "appliedenergistics2", "AWWayofTime", "Baubles", "Thaumcraft", "Botania", "Avaritia", "bdlib", "BiblioCraft", "BiblioWoodsBoP", "CoFHCore", "Forestry", "BiblioWoodsForestry", "BiblioWoodsNatura", "ThermalFoundation", "ThermalExpansion", "BigReactors", "BinnieCore", "Botany", "ExtraBees", "ExtraTrees", "Genetics", "BiomeTweaker", "BrandonsCore", "BuildCraft|Core", "BuildCraft|Builders", "BuildCraft|Transport", "BuildCraft|Energy", "BuildCraft|Silicon", "BuildCraft|Robotics", "BuildCraft|Factory", "BuildCraft|Compat", "CarpentersBlocks", "Railcraft", "ForgeMultipart", "chisel", "ComputerCraft", "cookingbook", "endercore", "customthings", "PTRModelLib", "props", "DraconicEvolution", "MineFactoryReloaded", "Waila", "EnderIO", "EnderStorage", "EnderTech", "exnihilo", "RedstoneArsenal", "ExtraUtilities", "ImmersiveEngineering", "Mantle", "TConstruct", "exastris", "excompressum", "extracells", "fastleafdecay", "ThaumicTinkerer", "ForbiddenMagic", "forgeanalytics", "FTBI", "MineTweaker3", "FTBL", "ftbtrophies", "FTBU", "funkylocomotion", "MagicBees", "gendustry", "GraviSuite", "guideapi", "IC2NuclearControl", "immersiveintegration", "inpure|core", "inventorytweaks", "IronChest", "JABBA", "kleeslabs", "LogisticsPipes", "MineFactoryReloaded|CompatAppliedEnergistics", "MineFactoryReloaded|CompatBuildCraft", "MineFactoryReloaded|CompatForestry", "MineFactoryReloaded|CompatForgeMicroblock", "MineFactoryReloaded|CompatIC2", "MrTJPCoreMod", "ProjRed|Core", "ProjRed|Exploration", "MineFactoryReloaded|CompatProjRed", "MineFactoryReloaded|CompatRailcraft", "MineFactoryReloaded|CompatThaumcraft", "MineFactoryReloaded|CompatThermalExpansion", "MineFactoryReloaded|CompatTConstruct", "MineFactoryReloaded|CompatVanilla", "modtweaker2", "Morpheus", "NEIAddons", "NEIAddons|Developer", "NEIAddons|AppEng", "NEIAddons|Botany", "NEIAddons|Forestry", "NEIAddons|CraftingTables", "NEIAddons|ExNihilo", "neiintegration", "OpenMods", "OpenBlocks", "OpenPeripheralCore", "OpenPeripheral", "OpenPeripheralIntegration", "harvestcraft", "ProjRed|Transmission", "ProjRed|Transportation", "ProjRed|Compatibility", "ProjRed|Integration", "ProjRed|Illumination", "ProjRed|Expansion", "rftools", "simplyjetpacks", "SolarExpansion", "StevesCarts", "StorageDrawers", "StorageDrawersBop", "StorageDrawersForestry", "StorageDrawersMisc", "StorageDrawersNatura", "tcinventoryscan", "thaumcraftneiplugin", "thaumicenergistics", "ThaumicExploration", "ThermalDynamics", "TiCTooltips", "TMechworks", "WailaHarvestability", "wawla", "witchery", "WR-CBE|Core", "WR-CBE|Addons", "WR-CBE|Logic", "YUNoMakeGoodMap", "McMultipart", "ForgeRelocation", "MCFrames", "RelocationFMP", "aobd", "IguanaTweaksTConstruct", "ForgeMicroblock"], "gamemode": null, "port": 25565, "state": "whitelist", "version": "1.7.10", "online": true, "protocol_version": 5, "max_player_count": 20, "level_type": null, "description": "A Minecraft Server", "brand": null, "welcome": null, "difficulty": null, "host": "75.145.57.253", "help_p1": null, "player_count": 0, "players": null, "error": "Invalid token", "hardcore": null, "software": null}
{"whitelist": null, "plugins": null, "signs": [], "id": 6374, "plugins_fml": null, "gamemode": null, "port": 25565, "state": "whitelist", "version": "Spigot 1.9.2", "online": true, "protocol_version": 109, "max_player_count": 20, "level_type": null, "description": "Serveur en construction", "brand": null, "welcome": null, "difficulty": null, "host": "93.26.154.139", "help_p1": null, "player_count": 0, "players": null, "error": "Invalid token", "hardcore": null, "software": null}
{"whitelist": null, "plugins": null, "signs": [], "id": 182714, "plugins_fml": null, "gamemode": null, "port": 25565, "state": "whitelist", "version": "1.7.9", "online": true, "protocol_version": 5, "max_player_count": 20, "level_type": null, "description": "A Minecraft Server", "brand": null, "welcome": null, "difficulty": null, "host": "173.230.152.54", "help_p1": null, "player_count": 0, "players": null, "error": "Invalid token", "hardcore": null, "software": null}
{"whitelist": null, "plugins": null, "signs": [], "id": 23159, "plugins_fml": [], "gamemode": null, "port": 25565, "state": "whitelist", "version": "BungeeCord 1.8.x, 1.9", "online": true, "protocol_version": 107, "max_player_count": 5000, "level_type": null, "description": "StripeMC | Minigames", "brand": null, "welcome": null, "difficulty": null, "host": "52.29.120.186", "help_p1": null, "player_count": 1260, "players": [], "error": "Error occurred while authenticating. Try again later.", "hardcore": null, "software": null}
{"whitelist": null, "plugins": null, "signs": [], "id": 263611, "plugins_fml": [], "gamemode": null, "port": 25565, "state": "whitelist", "version": "BungeeCord 1.8.x, 1.9.x", "online": true, "protocol_version": 109, "max_player_count": 1000, "level_type": null, "description": "          ---  PowerFul-MC Network  ---           >>> Try Out FunTools! Just Type /Funtools  <<<", "brand": null, "welcome": null, "difficulty": null, "host": "192.99.207.203", "help_p1": null, "player_count": 1, "players": null, "error": "Invalid token", "hardcore": null, "software": null}
{"whitelist": null, "plugins": null, "signs": [], "id": 78472, "plugins_fml": null, "gamemode": null, "port": 25565, "state": "whitelist", "version": "Spigot 1.8", "online": true, "protocol_version": 47, "max_player_count": 4, "level_type": null, "description": "gerold.nitrado.net !!! welcome to my house!!!", "brand": null, "welcome": null, "difficulty": null, "host": "217.198.140.194", "help_p1": null, "player_count": 1, "players": ["AwesomePlayerJoe"], "error": "Invalid token", "hardcore": null, "software": null}
{"whitelist": null, "plugins": null, "signs": [], "id": 299067, "plugins_fml": ["mcp", "FML", "Forge", "appliedenergistics2-core", "CodeChickenCore", "NotEnoughItems", "ThE-core", "ThaumicTinkerer-preloader", "ChocoPatcher", "OpenModsCore", "<CoFH ASM>", "BinniePatcher", "FastCraft", "IC2", "AdvancedSolarPanel", "AgriCraft", "appliedenergistics2", "AWWayofTime", "Baubles", "Thaumcraft", "Botania", "Avaritia", "bdlib", "BiblioCraft", "BiblioWoodsBoP", "CoFHCore", "Forestry", "BiblioWoodsForestry", "BiblioWoodsNatura", "ThermalFoundation", "ThermalExpansion", "BigReactors", "BinnieCore", "Botany", "ExtraBees", "ExtraTrees", "Genetics", "BiomeTweaker", "BrandonsCore", "BuildCraft|Core", "BuildCraft|Builders", "BuildCraft|Transport", "BuildCraft|Energy", "BuildCraft|Silicon", "BuildCraft|Robotics", "BuildCraft|Factory", "BuildCraft|Compat", "CarpentersBlocks", "Railcraft", "ForgeMultipart", "chisel", "ComputerCraft", "cookingbook", "endercore", "customthings", "PTRModelLib", "props", "DraconicEvolution", "MineFactoryReloaded", "Waila", "EnderIO", "EnderStorage", "EnderTech", "exnihilo", "RedstoneArsenal", "ExtraUtilities", "ImmersiveEngineering", "Mantle", "TConstruct", "exastris", "excompressum", "extracells", "fastleafdecay", "ThaumicTinkerer", "ForbiddenMagic", "forgeanalytics", "FTBI", "MineTweaker3", "FTBL", "ftbtrophies", "FTBU", "funkylocomotion", "MagicBees", "gendustry", "GraviSuite", "guideapi", "IC2NuclearControl", "immersiveintegration", "inpure|core", "inventorytweaks", "IronChest", "JABBA", "kleeslabs", "LogisticsPipes", "MineFactoryReloaded|CompatAppliedEnergistics", "MineFactoryReloaded|CompatBuildCraft", "MineFactoryReloaded|CompatForestry", "MineFactoryReloaded|CompatForgeMicroblock", "MineFactoryReloaded|CompatIC2", "MrTJPCoreMod", "ProjRed|Core", "ProjRed|Exploration", "MineFactoryReloaded|CompatProjRed", "MineFactoryReloaded|CompatRailcraft", "MineFactoryReloaded|CompatThaumcraft", "MineFactoryReloaded|CompatThermalExpansion", "MineFactoryReloaded|CompatTConstruct", "MineFactoryReloaded|CompatVanilla", "modtweaker2", "Morpheus", "NEIAddons", "NEIAddons|Developer", "NEIAddons|AppEng", "NEIAddons|Botany", "NEIAddons|Forestry", "NEIAddons|CraftingTables", "NEIAddons|ExNihilo", "neiintegration", "OpenMods", "OpenBlocks", "OpenPeripheralCore", "OpenPeripheral", "OpenPeripheralIntegration", "harvestcraft", "ProjRed|Transmission", "ProjRed|Transportation", "ProjRed|Compatibility", "ProjRed|Integration", "ProjRed|Illumination", "ProjRed|Expansion", "rftools", "simplyjetpacks", "SolarExpansion", "StevesCarts", "StorageDrawers", "StorageDrawersBop", "StorageDrawersForestry", "StorageDrawersMisc", "StorageDrawersNatura", "tcinventoryscan", "thaumcraftneiplugin", "thaumicenergistics", "ThaumicExploration", "ThermalDynamics", "TiCTooltips", "TMechworks", "WailaHarvestability", "wawla", "witchery", "WR-CBE|Core", "WR-CBE|Addons", "WR-CBE|Logic", "YUNoMakeGoodMap", "McMultipart", "ForgeRelocation", "MCFrames", "RelocationFMP", "aobd", "IguanaTweaksTConstruct", "ForgeMicroblock"], "gamemode": null, "port": 25565, "state": "whitelist", "version": "1.7.10", "online": true, "protocol_version": 5, "max_player_count": 20, "level_type": null, "description": "A Minecraft Server", "brand": null, "welcome": null, "difficulty": null, "host": "65.175.137.140", "help_p1": null, "player_count": 0, "players": null, "error": "Invalid token", "hardcore": null, "software": null}
{"whitelist": null, "plugins": null, "signs": [], "id": 87647, "plugins_fml": ["mcp", "FML", "Forge", "lootplusplus", "lucky"], "gamemode": null, "port": 25565, "state": "whitelist", "version": "1.8", "online": true, "protocol_version": 47, "max_player_count": 4, "level_type": null, "description": "nitrado.net gameserver", "brand": null, "welcome": null, "difficulty": null, "host": "217.198.133.158", "help_p1": null, "player_count": 0, "players": null, "error": "This server requires FML/Forge to be installed. Contact your server admin for more details.", "hardcore": null, "software": null}
{"whitelist": null, "plugins": null, "signs": [], "id": 15595, "plugins_fml": null, "gamemode": null, "port": 25565, "state": "whitelist", "version": "1.9.2", "online": true, "protocol_version": 109, "max_player_count": 20, "level_type": null, "description": "A Minecraft Server", "brand": null, "welcome": null, "difficulty": null, "host": "91.121.103.133", "help_p1": null, "player_count": 0, "players": null, "error": "Invalid token", "hardcore": null, "software": null}
{"whitelist": null, "plugins": null, "signs": [], "id": 74976, "plugins_fml": null, "gamemode": null, "port": 25565, "state": "whitelist", "version": "1.9.2", "online": true, "protocol_version": 109, "max_player_count": 20, "level_type": null, "description": "A Minecraft Server Powered by Docker", "brand": null, "welcome": null, "difficulty": null, "host": "86.52.0.42", "help_p1": null, "player_count": 0, "players": null, "error": "Invalid token", "hardcore": null, "software": null}
{"whitelist": false, "plugins": "Plugins (1): PlayerMarkers", "signs": [{"y": 168, "x": 568, "z": 1077, "lines": ["Welcome to", "Ragecraft III:", "The Prophecy", "(version 1.4)"]}, {"y": 168, "x": 567, "z": 1077, "lines": ["Made by heliceo", "", "for Minecraft", "version 1.8.8"]}, {"y": 37, "x": 572, "z": 1060, "lines": ["PHARAOH BOSS", "", "", ""]}, {"y": 166, "x": 561, "z": 1070, "lines": ["Garfield2436", "Krose", "kaladun", "Omegaplayer02"]}, {"y": 167, "x": 561, "z": 1070, "lines": ["shudderfly", "Chipmunk46", "Browneye414", "TechAnimation"]}, {"y": 166, "x": 561, "z": 1069, "lines": ["RestInPeaceHBK", "Caecilleus", "soupbob", "iEnigmaaa"]}, {"y": 168, "x": 561, "z": 1070, "lines": ["A big \"thank", "you!\" to my", "beta testers!", ""]}, {"y": 168, "x": 574, "z": 1070, "lines": ["- MCEdit", "- WorldEdit", "- NBTExplorer", ""]}, {"y": 167, "x": 561, "z": 1069, "lines": ["Fangride", "Crafterdark", "_Gunter_", "Nbtrainor"]}, {"y": 167, "x": 574, "z": 1069, "lines": ["Special thanks", "to the creators", "of these tools", "as well as"]}, {"y": 168, "x": 561, "z": 1069, "lines": ["You guys have", "done an awesome", "job :-)", ""]}, {"y": 168, "x": 574, "z": 1069, "lines": ["The following", "tools were used", "in the creation", "of this map:"]}, {"y": 35, "x": 584, "z": 1048, "lines": ["Arcane Strike", "(all 4)", "", ""]}, {"y": 31, "x": 584, "z": 1044, "lines": ["Healing", "", "", ""]}, {"y": 35, "x": 584, "z": 1044, "lines": ["Divine Shield", "", "", ""]}, {"y": 35, "x": 584, "z": 1047, "lines": ["Arcane Strike", "(all 4)", "", ""]}, {"y": 35, "x": 584, "z": 1045, "lines": ["Divine Shield", "", "", ""]}, {"y": 166, "x": 566, "z": 1031, "lines": ["", "", "", ""]}, {"y": 167, "x": 568, "z": 1024, "lines": ["and books", "carefully!", "I promise it", "won't take long"]}, {"y": 167, "x": 567, "z": 1024, "lines": ["Please make", "sure to read", "all of the", "following signs"]}, {"y": 168, "x": 560, "z": 1014, "lines": ["RULES", "||", "||", "V"]}, {"y": 167, "x": 575, "z": 1013, "lines": ["<|=====", "Activate Death", "Counter", "<|====="]}, {"y": 168, "x": 560, "z": 1011, "lines": ["OBJECTIVES", "||", "||", "V"]}, {"y": 168, "x": 560, "z": 992, "lines": ["This map", "contains a lot", "of command", "block assisted"]}, {"y": 167, "x": 560, "z": 992, "lines": ["you find!", "Important", "information and", "hints are often"]}, {"y": 167, "x": 575, "z": 1004, "lines": ["Particles", "", "All", ""]}, {"y": 167, "x": 575, "z": 1002, "lines": ["Difficulty", "", "Easy - Hard", ""]}, {"y": 167, "x": 575, "z": 1003, "lines": ["MC Version", "", "1.8.8", ""]}, {"y": 168, "x": 575, "z": 1001, "lines": ["!!!!!!!!!!!!!!!!!!!!!!!!!!!!!", "REQUIRED", "SETTINGS", "!!!!!!!!!!!!!!!!!!!!!!!!!!!!!"]}, {"y": 167, "x": 575, "z": 1000, "lines": ["Render Distance", "", "8 or more", "chunks"]}, {"y": 168, "x": 575, "z": 1002, "lines": ["You MUST use", "these settings", "for the map to", "work properly!"]}, {"y": 167, "x": 575, "z": 1001, "lines": ["Memory allocated", "to Minecraft:", "At least 2 GB, but", "4 recommended!"]}, {"y": 167, "x": 575, "z": 999, "lines": ["GUI Scale", "", "Large or Normal", "[NOT auto!]"]}, {"y": 167, "x": 575, "z": 992, "lines": ["Graphics", "", "Fast", ""]}, {"y": 167, "x": 575, "z": 993, "lines": ["Clouds", "", "Off", ""]}, {"y": 167, "x": 560, "z": 1003, "lines": ["beta testers.", "Unfortunately,", "Minecraft has a", "habit of causing"]}, {"y": 167, "x": 560, "z": 1004, "lines": ["This map has", "been thoroughly", "tested by more", "than a dozen"]}, {"y": 167, "x": 560, "z": 1001, "lines": ["report them to", "me in the", "Minecraft forum.", ""]}, {"y": 167, "x": 560, "z": 1002, "lines": ["random bugs and", "glitches. If you", "find any of", "those, please"]}, {"y": 167, "x": 560, "z": 999, "lines": ["thread in your", "video", "description!", ""]}, {"y": 167, "x": 560, "z": 1000, "lines": ["If you are an", "LPer, please", "link the original", "Ragecraft"]}, {"y": 168, "x": 575, "z": 982, "lines": ["Multiplayer", "information", "||", "V"]}, {"y": 167, "x": 560, "z": 991, "lines": ["\"hidden\" in", "lore texts, but", "they are", "usually easy"]}, {"y": 168, "x": 560, "z": 990, "lines": ["abilities.", "Make sure to", "read all books", "and signs that"]}, {"y": 168, "x": 560, "z": 991, "lines": ["mechanics,", "sub-objectives", "and items with", "special"]}, {"y": 167, "x": 560, "z": 990, "lines": ["to figure out.", "Most texts are", "short and", "concise."]}, {"y": 168, "x": 560, "z": 982, "lines": ["Additional", "Hints", "||", "V"]}, {"y": 167, "x": 575, "z": 990, "lines": ["Render Distance", "", "12 - 16 Chunks", ""]}, {"y": 167, "x": 575, "z": 991, "lines": ["Difficulty", "", "Normal", ""]}, {"y": 167, "x": 575, "z": 989, "lines": ["RECOMMENDED", "SETTINGS", "[for balance", "& performance]"]}, {"y": 167, "x": 568, "z": 972, "lines": ["Ready?", "Start the map!", "", "<|====="]}, {"y": 169, "x": 567, "z": 972, "lines": ["IMPORTANT", "---------------", "If more players", "join the map"]}, {"y": 169, "x": 568, "z": 972, "lines": ["later on, they", "have to press", "this button as", "well."]}], "id": 268708, "plugins_fml": null, "gamemode": 0, "port": 25565, "state": "help", "version": "CraftBukkit 1.8.8", "online": true, "protocol_version": 47, "max_player_count": 20, "level_type": "default", "description": "A Minecraft Server", "brand": "CraftBukkit", "welcome": null, "difficulty": 1, "host": "5.196.177.184", "help_p1": "--------- Help: Index (1/2) --------------------- Use /help [n] to get page n of help. Aliases: Lists command aliases Bukkit: All commands for Bukkit Minecraft: All commands for Minecraft /help: Shows the help menu /me: A Mojang provided command. /minecraft:tell: A Mojang provided command. /plugins: Gets a list of plugins running on the ... /tell: A Mojang provided command.", "player_count": 0, "players": null, "error": null, "hardcore": false, "software": "This server is running CraftBukkit version git-Bukkit-9935adc (MC: 1.8.8) (Implementing API version 1.8.8-R0.1-SNAPSHOT) Checking version, please wait..."}
{"whitelist": null, "plugins": null, "signs": [], "id": 172318, "plugins_fml": null, "gamemode": null, "port": 25565, "state": "whitelist", "version": "Spigot 1.8.7", "online": true, "protocol_version": 47, "max_player_count": 10, "level_type": null, "description": "Offizieller EasyTec Minecraft Leben-Survival-Server", "brand": null, "welcome": null, "difficulty": null, "host": "85.190.173.158", "help_p1": null, "player_count": 0, "players": null, "error": "Invalid token", "hardcore": null, "software": null}
{"whitelist": null, "plugins": null, "signs": [], "id": 9253, "plugins_fml": null, "gamemode": null, "port": 25565, "state": "whitelist", "version": "1.9", "online": true, "protocol_version": 107, "max_player_count": 6, "level_type": null, "description": "nitrado.net gameserver", "brand": null, "welcome": null, "difficulty": null, "host": "31.214.166.4", "help_p1": null, "player_count": 0, "players": null, "error": "Invalid token", "hardcore": null, "software": null}
{"whitelist": null, "plugins": null, "signs": [], "id": 54660, "plugins_fml": ["mcp", "FML", "Forge", "CodeChickenCore", "ivtoolkit", "NotEnoughItems", "RenderPlayerAPI", "OpenModsCore", "<CoFH ASM>", "FastCraft", "furnace3d", "DC1", "Boost", "abyssalcraft", "CoFHCore", "advancedgenetics", "animalbikes", "hoverboard", "Mantle", "Natura", "BiomesOPlenty", "Forestry", "MineFactoryReloaded", "Artifice", "BattleTowers", "Baubles", "bdlib", "betterstorage", "bettervillages", "BiblioCraft", "BiblioWoodsBoP", "BiblioWoodsForestry", "BiblioWoodsNatura", "AWWayofTime", "WaslieCore", "BloodUtils", "redgear_core", "redgear_brewcraft", "CarpentersBlocks", "chancecubes", "ChickenChunks", "ForgeMultipart", "chisel", "compactstorage", "cookingbook", "BuildMod", "CoroPets", "CoroAI", "ExtendedRenderer", "ConfigMod", "creativecore", "customnpcs", "PTRModelLib", "props", "doge", "Emotes", "endercore", "EnderStorage", "ThermalFoundation", "ThermalExpansion", "evilcraft", "ExtraUtilities", "harvestcraft", "TConstruct", "ExtraTiC", "flansmod", "fossil", "MineTweaker3", "FTBL", "FTBU", "advgenerators", "guideapi", "iChunUtil", "Hats", "InventoryPets", "JABBA", "k4lib", "reaper_lantern", "SlimevoidLib", "LittleBlocks", "lootplusplus", "malisiscore", "malisisdoors", "mo", "MineFactoryReloaded|CompatForestry", "MineFactoryReloaded|CompatForgeMicroblock", "MrTJPCoreMod", "ProjRed|Core", "ProjRed|Exploration", "MineFactoryReloaded|CompatProjRed", "MineFactoryReloaded|CompatThermalExpansion", "MineFactoryReloaded|CompatTConstruct", "MineFactoryReloaded|CompatVanilla", "minestones", "MTRM", "modtweaker2", "numina", "powersuits", "MSM3", "moreplayermodels", "Morph", "cfm", "neiintegration", "Oceancraft", "OpenMods", "OpenBlocks", "ProjRed|Transmission", "ProjRed|Transportation", "ProjRed|Compatibility", "ProjRed|Integration", "ProjRed|Illumination", "ProjRed|Expansion", "quiverchevsky", "RandomThings", "reccomplex", "Sanguimancy", "SanguineExtras", "secretroomsmod", "StorageDrawers", "TF2Teleporter", "erebus", "ThermalDynamics", "TiCTooltips", "tradeboothmod", "TrailMix", "trashslot", "universalcoins", "VillagersNose", "Waterproof", "weather2", "McMultipart", "ForgeRelocation", "MCFrames", "RelocationFMP", "ForgeMicroblock"], "gamemode": null, "port": 25565, "state": "whitelist", "version": "1.7.10", "online": true, "protocol_version": 5, "max_player_count": 20, "level_type": null, "description": "A Minecraft Server", "brand": null, "welcome": null, "difficulty": null, "host": "24.231.160.235", "help_p1": null, "player_count": 0, "players": null, "error": "Invalid token", "hardcore": null, "software": null}
{"whitelist": null, "plugins": null, "signs": [], "id": 209087, "plugins_fml": ["mcp", "FML", "Forge", "appliedenergistics2-core", "Aroma1997Core", "CodeChickenCore", "NotEnoughItems", "PlayerAPI", "OpenModsCore", "<CoFH ASM>", "battlegear2", "act", "appliedenergistics2", "Aroma1997CoreHelper", "BiblioCraft", "ExtrabiomesXL", "BiblioWoodsEBXL", "CoFHCore", "ThermalFoundation", "ThermalExpansion", "BigReactors", "CarpentersBlocks", "Railcraft", "ForgeMultipart", "chisel", "ctmlib", "EnderStorage", "Mantle", "MineFactoryReloaded", "Waila", "TConstruct", "ExtraUtilities", "FastCraft", "fastleafdecay", "flansmod", "funkylocomotion", "HardcoreDarkness", "inpure|core", "inventorytweaks", "IronChest", "JABBA", "JourneyMapServer", "mcheli", "MineFactoryReloaded|CompatAppliedEnergistics", "MineFactoryReloaded|CompatAtum", "MineFactoryReloaded|CompatBackTools", "MineFactoryReloaded|CompatBuildCraft", "MineFactoryReloaded|CompatChococraft", "MineFactoryReloaded|CompatExtraBiomes", "MineFactoryReloaded|CompatForestry", "MineFactoryReloaded|CompatForgeMicroblock", "MineFactoryReloaded|CompatIC2", "MineFactoryReloaded|CompatMystcraft", "MrTJPCoreMod", "ProjRed|Core", "ProjRed|Exploration", "MineFactoryReloaded|CompatProjRed", "MineFactoryReloaded|CompatRailcraft", "MineFactoryReloaded|CompatSufficientBiomes", "MineFactoryReloaded|CompatThaumcraft", "MineFactoryReloaded|CompatThermalExpansion", "MineFactoryReloaded|CompatTConstruct", "MineFactoryReloaded|CompatTwilightForest", "MineFactoryReloaded|CompatVanilla", "MineTweaker3", "MobProperties", "numina", "powersuits", "Morpheus", "NaturalAbsorption", "NEIAddons", "NEIAddons|Developer", "NEIAddons|AppEng", "NEIAddons|Botany", "NEIAddons|Forestry", "NEIAddons|CraftingTables", "NEIAddons|ExNihilo", "neiintegration", "OpenMods", "OpenBlocks", "openmodularturrets", "PneumaticCraft", "ProjRed|Transmission", "ProjRed|Transportation", "ProjRed|Compatibility", "ProjRed|Integration", "ProjRed|Illumination", "ProjRed|Expansion", "RedstoneArsenal", "secretroomsmod", "SolarExpansion", "SpecialMobs", "ThermalDynamics", "tinkersdefense", "TMechworks", "Translocator", "ttCore", "WailaHarvestability", "wawla", "WR-CBE|Core", "WR-CBE|Addons", "WR-CBE|Logic", "McMultipart", "ForgeRelocation", "MCFrames", "RelocationFMP", "ForgeMicroblock"], "gamemode": null, "port": 25565, "state": "whitelist", "version": "1.7.10", "online": true, "protocol_version": 5, "max_player_count": 4, "level_type": null, "description": "nitrado.net gameserver", "brand": null, "welcome": null, "difficulty": null, "host": "85.131.150.179", "help_p1": null, "player_count": 0, "players": null, "error": "Invalid token", "hardcore": null, "software": null}
{"whitelist": null, "plugins": null, "signs": [], "id": 183309, "plugins_fml": ["mcp", "FML", "Forge", "appliedenergistics2-core", "Aroma1997Core", "CartFixes", "CodeChickenCore", "ivtoolkit", "Micdoodlecore", "NotEnoughItems", "OpenComputers|Core", "PlayerAPI", "ThaumicTinkerer-preloader", "OpenModsCore", "<CoFH ASM>", "debug", "bspkrsCore", "Treecapitator", "IC2", "AdvancedMachines", "appliedenergistics2", "Aroma1997CoreHelper", "Aroma1997sDimension", "AromaBackup", "CoFHCore", "asielib", "iChunUtil", "Grinder", "Backpack", "bdlib", "BiblioCraft", "Mantle", "Natura", "BiomesOPlenty", "BiblioWoodsBoP", "HardcoreEnderExpansion", "BuildCraft|Core", "Forestry", "BiblioWoodsForestry", "BiblioWoodsNatura", "Baubles", "ThermalFoundation", "ThermalExpansion", "BigReactors", "BinnieCore", "Botany", "ExtraBees", "ExtraTrees", "Genetics", "AWWayofTime", "Thaumcraft", "Botania", "BuildCraft|Silicon", "BuildCraft|Factory", "BuildCraft|Builders", "BuildCraft|Energy", "BuildCraft|Robotics", "BuildCraft|Transport", "BuildCraft|Compat", "CarpentersBlocks", "ChickenChunks", "Railcraft", "TwilightForest", "ForgeMultipart", "chisel", "colorchat", "CompactSolars", "ComputerCraft", "endercore", "MineFactoryReloaded", "Waila", "EnderIO", "EnderStorage", "MrTJPCoreMod", "ProjRed|Core", "ProjRed|Transmission", "OpenComputers", "GalacticraftCore", "Mekanism", "computronics", "DeathCounter", "Doge", "eplus", "EnderTech", "EnderZoo", "extracells", "TConstruct", "ExtraUtilities", "factorization.notify", "factorization", "factorization.misc", "FastCraft", "fastleafdecay", "flansmod", "ThaumicTinkerer", "ForbiddenMagic", "funkylocomotion", "GalacticraftMars", "MagicBees", "gendustry", "GraviSuite", "Growthcraft", "Growthcraft|Cellar", "Growthcraft|Apples", "Growthcraft|Bamboo", "Growthcraft|Bees", "Growthcraft|Fishtrap", "Growthcraft|Grapes", "Growthcraft|Hops", "Growthcraft|Rice", "Hats", "HatStand", "HelpFixer", "HardcoreQuesting", "IC2NuclearControl", "inpure|core", "IronChest", "JABBA", "LogisticsPipes", "magicalcrops", "MekanismGenerators", "MekanismTools", "MineFactoryReloaded|CompatAppliedEnergistics", "MineFactoryReloaded|CompatAtum", "MineFactoryReloaded|CompatBackTools", "MineFactoryReloaded|CompatBuildCraft", "MineFactoryReloaded|CompatChococraft", "MineFactoryReloaded|CompatExtraBiomes", "MineFactoryReloaded|CompatForestry", "MineFactoryReloaded|CompatForgeMicroblock", "MineFactoryReloaded|CompatIC2", "Mystcraft", "MineFactoryReloaded|CompatMystcraft", "ProjRed|Exploration", "MineFactoryReloaded|CompatProjRed", "MineFactoryReloaded|CompatRailcraft", "MineFactoryReloaded|CompatSufficientBiomes", "MineFactoryReloaded|CompatThaumcraft", "MineFactoryReloaded|CompatThermalExpansion", "MineFactoryReloaded|CompatTConstruct", "MineFactoryReloaded|CompatTwilightForest", "MineFactoryReloaded|CompatVanilla", "MineFactoryReloaded|CompatMagicalCrops", "MineMenu", "testdummy", "numina", "powersuits", "powersuitaddons", "Morph", "Morpheus", "cfm", "necromancy", "NEIAddons", "NEIAddons|Developer", "NEIAddons|AppEng", "NEIAddons|Botany", "NEIAddons|Forestry", "NEIAddons|CraftingTables", "NEIAddons|ExNihilo", "neiintegration", "NetherOres", "recipemod", "neresources", "ObsidiPlates", "OpenMods", "OpenBlocks", "OpenPeripheralCore", "OpenPeripheral", "OpenPeripheralIntegration", "harvestcraft", "PneumaticCraft", "progressiveautomation", "ProjRed|Transportation", "ProjRed|Compatibility", "ProjRed|Integration", "ProjRed|Fabrication", "ProjRed|Illumination", "ProjRed|Expansion", "reccomplex", "RedstoneArsenal", "RefinedRelocation", "libsandstone", "xreliquary", "Roguelike", "simplyjetpacks", "squidless", "statues", "StevesFactoryManager", "StevesAddons", "StevesCarts", "StevesWorkshop", "Sync", "thaumcraftneiplugin", "ThaumicExploration", "ThermalDynamics", "TMechworks", "Translocator", "wailaplugins", "warpbook", "witchery", "WR-CBE|Core", "WR-CBE|Addons", "WR-CBE|Logic", "yampst", "McMultipart", "ForgeRelocation", "MCFrames", "RelocationFMP", "aobd", "denseores", "ForgeMicroblock"], "gamemode": null, "port": 25565, "state": "whitelist", "version": "1.7.10", "online": true, "protocol_version": 5, "max_player_count": 4, "level_type": null, "description": "nitrado.net gameserver", "brand": null, "welcome": null, "difficulty": null, "host": "217.198.137.44", "help_p1": null, "player_count": 0, "players": null, "error": "Invalid token", "hardcore": null, "software": null}
{"whitelist": null, "plugins": null, "signs": [], "id": 302414, "plugins_fml": null, "gamemode": null, "port": 25565, "state": "whitelist", "version": "1.9.1-pre3", "online": true, "protocol_version": 108, "max_player_count": 10, "level_type": null, "description": "A minecraft server", "brand": null, "welcome": null, "difficulty": null, "host": "173.199.82.181", "help_p1": null, "player_count": 0, "players": null, "error": "Invalid token", "hardcore": null, "software": null}
{"whitelist": null, "plugins": null, "signs": [], "id": 240707, "plugins_fml": ["mcp", "FML", "Forge", "appliedenergistics2-core", "CodeChickenCore", "NotEnoughItems", "ThE-core", "ThaumicTinkerer-preloader", "ChocoPatcher", "OpenModsCore", "<CoFH ASM>", "BinniePatcher", "FastCraft", "IC2", "AdvancedSolarPanel", "AgriCraft", "appliedenergistics2", "AWWayofTime", "Baubles", "Thaumcraft", "Botania", "Avaritia", "bdlib", "BiblioCraft", "BiblioWoodsBoP", "CoFHCore", "Forestry", "BiblioWoodsForestry", "BiblioWoodsNatura", "ThermalFoundation", "ThermalExpansion", "BigReactors", "BinnieCore", "Botany", "ExtraBees", "ExtraTrees", "Genetics", "BiomeTweaker", "BrandonsCore", "BuildCraft|Core", "BuildCraft|Builders", "BuildCraft|Transport", "BuildCraft|Energy", "BuildCraft|Silicon", "BuildCraft|Robotics", "BuildCraft|Factory", "BuildCraft|Compat", "CarpentersBlocks", "Railcraft", "ForgeMultipart", "chisel", "ComputerCraft", "cookingbook", "endercore", "customthings", "PTRModelLib", "props", "DraconicEvolution", "MineFactoryReloaded", "Waila", "EnderIO", "EnderStorage", "EnderTech", "exnihilo", "RedstoneArsenal", "ExtraUtilities", "ImmersiveEngineering", "Mantle", "TConstruct", "exastris", "excompressum", "extracells", "fastleafdecay", "ThaumicTinkerer", "ForbiddenMagic", "forgeanalytics", "FTBI", "MineTweaker3", "FTBL", "ftbtrophies", "FTBU", "funkylocomotion", "MagicBees", "gendustry", "GraviSuite", "guideapi", "IC2NuclearControl", "immersiveintegration", "inpure|core", "inventorytweaks", "IronChest", "JABBA", "kleeslabs", "LogisticsPipes", "MineFactoryReloaded|CompatAppliedEnergistics", "MineFactoryReloaded|CompatBuildCraft", "MineFactoryReloaded|CompatForestry", "MineFactoryReloaded|CompatForgeMicroblock", "MineFactoryReloaded|CompatIC2", "MrTJPCoreMod", "ProjRed|Core", "ProjRed|Exploration", "MineFactoryReloaded|CompatProjRed", "MineFactoryReloaded|CompatRailcraft", "MineFactoryReloaded|CompatThaumcraft", "MineFactoryReloaded|CompatThermalExpansion", "MineFactoryReloaded|CompatTConstruct", "MineFactoryReloaded|CompatVanilla", "modtweaker2", "Morpheus", "NEIAddons", "NEIAddons|Developer", "NEIAddons|AppEng", "NEIAddons|Botany", "NEIAddons|Forestry", "NEIAddons|CraftingTables", "NEIAddons|ExNihilo", "neiintegration", "OpenMods", "OpenBlocks", "OpenPeripheralCore", "OpenPeripheral", "OpenPeripheralIntegration", "harvestcraft", "ProjRed|Transmission", "ProjRed|Transportation", "ProjRed|Compatibility", "ProjRed|Integration", "ProjRed|Illumination", "ProjRed|Expansion", "rftools", "simplyjetpacks", "SolarExpansion", "StevesCarts", "StorageDrawers", "StorageDrawersBop", "StorageDrawersForestry", "StorageDrawersMisc", "StorageDrawersNatura", "tcinventoryscan", "thaumcraftneiplugin", "thaumicenergistics", "ThaumicExploration", "ThermalDynamics", "TiCTooltips", "TMechworks", "WailaHarvestability", "wawla", "witchery", "WR-CBE|Core", "WR-CBE|Addons", "WR-CBE|Logic", "YUNoMakeGoodMap", "McMultipart", "ForgeRelocation", "MCFrames", "RelocationFMP", "aobd", "IguanaTweaksTConstruct", "ForgeMicroblock"], "gamemode": null, "port": 25565, "state": "whitelist", "version": "1.7.10", "online": true, "protocol_version": 5, "max_player_count": 96, "level_type": null, "description": "A Minecraft Server", "brand": null, "welcome": null, "difficulty": null, "host": "158.69.172.181", "help_p1": null, "player_count": 0, "players": null, "error": "Invalid token", "hardcore": null, "software": null}
{"whitelist": null, "plugins": null, "signs": [], "id": 292601, "plugins_fml": null, "gamemode": null, "port": 25565, "state": "whitelist", "version": "1.8.9", "online": true, "protocol_version": 47, "max_player_count": 200, "level_type": null, "description": "A Minecraft Server", "brand": null, "welcome": null, "difficulty": null, "host": "198.50.141.86", "help_p1": null, "player_count": 0, "players": null, "error": "Invalid token", "hardcore": null, "software": null}
{"whitelist": null, "plugins": null, "signs": [], "id": 244845, "plugins_fml": null, "gamemode": null, "port": 25565, "state": "whitelist", "version": "1.8.9", "online": true, "protocol_version": 47, "max_player_count": 4, "level_type": null, "description": "nitrado.net gameserver", "brand": null, "welcome": null, "difficulty": null, "host": "46.251.240.59", "help_p1": null, "player_count": 2, "players": ["maybeCan", "maybeMac"], "error": "Invalid token", "hardcore": null, "software": null}
{"whitelist": null, "plugins": null, "signs": [], "id": 122498, "plugins_fml": null, "gamemode": null, "port": 25565, "state": "whitelist", "version": "CraftBukkit 1.8.8", "online": true, "protocol_version": 47, "max_player_count": 1000, "level_type": null, "description": "Welcome to our Minecraft Server!  Please enjoy your stay!  Thank You.  --Admin", "brand": null, "welcome": null, "difficulty": null, "host": "158.69.140.236", "help_p1": null, "player_count": 0, "players": null, "error": "Invalid token", "hardcore": null, "software": null}
{"whitelist": null, "plugins": null, "signs": [], "id": 106240, "plugins_fml": null, "gamemode": null, "port": 25565, "state": "whitelist", "version": "1.9.2", "online": true, "protocol_version": 109, "max_player_count": 12, "level_type": null, "description": "A Minecraft Server", "brand": null, "welcome": null, "difficulty": null, "host": "104.219.5.26", "help_p1": null, "player_count": 0, "players": null, "error": "Invalid token", "hardcore": null, "software": null}
{"whitelist": null, "plugins": null, "signs": [], "id": 51147, "plugins_fml": null, "gamemode": null, "port": 25565, "state": "whitelist", "version": "Spigot 1.8.8", "online": true, "protocol_version": 47, "max_player_count": 8, "level_type": null, "description": "A Minecraft Server", "brand": null, "welcome": null, "difficulty": null, "host": "199.202.218.40", "help_p1": null, "player_count": 0, "players": null, "error": "Invalid token", "hardcore": null, "software": null}
{"whitelist": null, "plugins": null, "signs": [], "id": 162256, "plugins_fml": null, "gamemode": null, "port": 25565, "state": "whitelist", "version": "Paper 1.9.2", "online": true, "protocol_version": 109, "max_player_count": 30, "level_type": null, "description": "                        \u2192 POWDERCRAFT \u2190 \n                  [PVP> Adventure <Prison]", "brand": null, "welcome": null, "difficulty": null, "host": "pow.us.to", "help_p1": null, "player_count": 0, "players": ["Hello, New Player.", "Come join! :)"], "error": "Invalid token", "hardcore": null, "software": null}
{"whitelist": null, "plugins": null, "signs": [], "id": 226698, "plugins_fml": null, "gamemode": null, "port": 25565, "state": "whitelist", "version": "1.9.2", "online": true, "protocol_version": 109, "max_player_count": 20, "level_type": null, "description": "A Minecraft Server", "brand": null, "welcome": null, "difficulty": null, "host": "96.2.117.94", "help_p1": null, "player_count": 0, "players": null, "error": "Invalid token", "hardcore": null, "software": null}
{"whitelist": null, "plugins": null, "signs": [], "id": 145960, "plugins_fml": null, "gamemode": null, "port": 25565, "state": "whitelist", "version": "CraftBukkit 1.7.9", "online": true, "protocol_version": 5, "max_player_count": 150, "level_type": null, "description": "A Minecraft Server", "brand": null, "welcome": null, "difficulty": null, "host": "92.222.215.64", "help_p1": null, "player_count": 0, "players": null, "error": "Invalid token", "hardcore": null, "software": null}
{"whitelist": null, "plugins": null, "signs": [], "id": 70532, "plugins_fml": null, "gamemode": null, "port": 25565, "state": "whitelist", "version": "Spigot 1.8.6", "online": true, "protocol_version": 47, "max_player_count": 36, "level_type": null, "description": "A Minecraft Server", "brand": null, "welcome": null, "difficulty": null, "host": "198.27.80.83", "help_p1": null, "player_count": 1, "players": ["secretman212"], "error": "Invalid token", "hardcore": null, "software": null}
{"whitelist": null, "plugins": null, "signs": [], "id": 262193, "plugins_fml": null, "gamemode": null, "port": 25565, "state": "whitelist", "version": "1.9", "online": true, "protocol_version": 109, "max_player_count": 200, "level_type": null, "description": "-------------> * StormRealms * <-------------\n   Custom Enchants - Factions - Custom Mounts", "brand": null, "welcome": null, "difficulty": null, "host": "23.254.0.26", "help_p1": null, "player_count": 0, "players": [], "error": "Invalid token", "hardcore": null, "software": null}
{"whitelist": null, "plugins": null, "signs": [], "id": 202662, "plugins_fml": ["mcp", "FML", "Forge", "appliedenergistics2-core", "CodeChickenCore", "NotEnoughItems", "ThE-core", "ThaumicTinkerer-preloader", "ChocoPatcher", "OpenModsCore", "<CoFH ASM>", "BinniePatcher", "FastCraft", "debug", "IC2", "AdvancedSolarPanel", "AgriCraft", "appliedenergistics2", "AWWayofTime", "Baubles", "Thaumcraft", "Botania", "Avaritia", "bdlib", "BiblioCraft", "Mantle", "Natura", "BiomesOPlenty", "BiblioWoodsBoP", "CoFHCore", "Forestry", "BiblioWoodsForestry", "BiblioWoodsNatura", "ThermalFoundation", "ThermalExpansion", "BigReactors", "BinnieCore", "Botany", "ExtraBees", "ExtraTrees", "Genetics", "BrandonsCore", "BuildCraft|Core", "BuildCraft|Builders", "BuildCraft|Transport", "BuildCraft|Energy", "BuildCraft|Silicon", "BuildCraft|Robotics", "BuildCraft|Factory", "BuildCraft|Compat", "CarpentersBlocks", "Railcraft", "TwilightForest", "ForgeMultipart", "chisel", "ComputerCraft", "PTRModelLib", "props", "DraconicEvolution", "endercore", "MineFactoryReloaded", "Waila", "EnderIO", "EnderStorage", "EnderTech", "EnderZoo", "extracells", "ExtraUtilities", "harvestcraft", "ImmersiveEngineering", "TConstruct", "ExtraTiC", "fastleafdecay", "ThaumicTinkerer", "ForbiddenMagic", "ForgeIRC", "MineTweaker3", "FTBL", "FTBT", "FTBU", "funkylocomotion", "RedstoneArsenal", "MagicBees", "gendustry", "GraviSuite", "guideapi", "iChunUtil", "Hats", "HatStand", "headcrumbs", "IC2NuclearControl", "immersiveintegration", "inpure|core", "inventorytweaks", "IronChest", "JABBA", "journeymap", "LogisticsPipes", "MineFactoryReloaded|CompatAppliedEnergistics", "MineFactoryReloaded|CompatBuildCraft", "MineFactoryReloaded|CompatForestry", "MineFactoryReloaded|CompatForgeMicroblock", "MineFactoryReloaded|CompatIC2", "MrTJPCoreMod", "ProjRed|Core", "ProjRed|Exploration", "MineFactoryReloaded|CompatProjRed", "MineFactoryReloaded|CompatRailcraft", "MineFactoryReloaded|CompatThaumcraft", "MineFactoryReloaded|CompatThermalExpansion", "MineFactoryReloaded|CompatTConstruct", "MineFactoryReloaded|CompatTwilightForest", "MineFactoryReloaded|CompatVanilla", "modtweaker2", "Morpheus", "Mystcraft", "NEIAddons", "NEIAddons|Developer", "NEIAddons|AppEng", "NEIAddons|Botany", "NEIAddons|Forestry", "NEIAddons|CraftingTables", "NEIAddons|ExNihilo", "neiintegration", "NetherOres", "neresources", "OpenMods", "OpenBlocks", "OpenPeripheralCore", "OpenPeripheral", "OpenPeripheralIntegration", "PortalGun", "ProjRed|Transmission", "ProjRed|Transportation", "ProjRed|Compatibility", "ProjRed|Integration", "ProjRed|Illumination", "ProjRed|Expansion", "rftools", "runicdungeons", "simplyjetpacks", "SolarExpansion", "springboards", "StevesFactoryManager", "StevesAddons", "StevesCarts", "StevesWorkshop", "StorageDrawers", "StorageDrawersBop", "StorageDrawersForestry", "StorageDrawersMisc", "StorageDrawersNatura", "tcinventoryscan", "thaumcraftneiplugin", "thaumicenergistics", "ThaumicExploration", "ThermalDynamics", "TiCTooltips", "TMechworks", "Translocator", "WailaHarvestability", "wawla", "witchery", "WR-CBE|Core", "WR-CBE|Addons", "WR-CBE|Logic", "McMultipart", "ForgeRelocation", "MCFrames", "RelocationFMP", "aobd", "denseores", "ForgeMicroblock"], "gamemode": null, "port": 25565, "state": "whitelist", "version": "1.7.10", "online": true, "protocol_version": 5, "max_player_count": 12, "level_type": null, "description": "Hosted by TwizZEffekt", "brand": null, "welcome": null, "difficulty": null, "host": "5.189.166.252", "help_p1": null, "player_count": 0, "players": null, "error": "Invalid token", "hardcore": null, "software": null}
{"whitelist": null, "plugins": null, "signs": [], "id": 285842, "plugins_fml": null, "gamemode": null, "port": 25565, "state": "whitelist", "version": "CraftBukkit 1.8.8", "online": true, "protocol_version": 47, "max_player_count": 30, "level_type": null, "description": "Best server ever!", "brand": null, "welcome": null, "difficulty": null, "host": "69.4.84.205", "help_p1": null, "player_count": 0, "players": null, "error": "Invalid token", "hardcore": null, "software": null}
{"whitelist": null, "plugins": null, "signs": [], "id": 273637, "plugins_fml": ["mcp", "FML", "Forge", "appliedenergistics2-core", "CodeChickenCore", "NotEnoughItems", "ThE-core", "ThaumicTinkerer-preloader", "OpenModsCore", "<CoFH ASM>", "BinniePatcher", "debug", "IC2", "AdvancedSolarPanel", "AgriCraft", "appliedenergistics2", "AWWayofTime", "Baubles", "Thaumcraft", "Botania", "Avaritia", "bdlib", "BiblioCraft", "Mantle", "Natura", "BiomesOPlenty", "BiblioWoodsBoP", "CoFHCore", "Forestry", "BiblioWoodsForestry", "BiblioWoodsNatura", "ThermalFoundation", "ThermalExpansion", "BigReactors", "BinnieCore", "Botany", "ExtraBees", "ExtraTrees", "Genetics", "BrandonsCore", "BuildCraft|Core", 